wks_com/__init__.py
wks_com/__main__.py
wks_com/constants.py
wks_com/helpers.py
wks_com/inverter.py
wks_com/types.py
wks_com/unpackers.py
wks_com/validators.py
wks_com-1.2.1.dist-info/METADATA
wks_com-1.2.1.dist-info/WHEEL
wks_com-1.2.1.dist-info/entry_points.txt
wks_com-1.2.1.dist-info/licenses/LICENSE.txt
wks_com-1.2.1.dist-info/RECORD
