Metadata-Version: 2.3
Name: wks-com
Version: 1.2.1
Summary: Communicate with your inverter (WKS EKO Circle).
Project-URL: Homepage, https://github.com/BoboTiG/python-wks-com
Project-URL: Changelog, https://github.com/BoboTiG/python-wks-com/blob/main/CHANGELOG.md
Project-URL: Source, https://github.com/BoboTiG/python-wks-com
Project-URL: Sponsor, https://github.com/sponsors/BoboTiG
Project-URL: Tracker, https://github.com/BoboTiG/python-wks-com/issues
Project-URL: Released Versions, https://github.com/BoboTiG/python-wks-com/releases
Author-email: Mickaël Schoentgen <contact@tiger-222.fr>
Maintainer-email: Mickaël Schoentgen <contact@tiger-222.fr>
License: MIT License
License-File: LICENSE.txt
Keywords: eko,inverter,rs232,serial,wks
Classifier: Development Status :: 5 - Production/Stable
Classifier: Intended Audience :: Developers
Classifier: Intended Audience :: Education
Classifier: Intended Audience :: Information Technology
Classifier: Intended Audience :: Science/Research
Classifier: License :: OSI Approved :: MIT License
Classifier: Operating System :: Unix
Classifier: Programming Language :: Python
Classifier: Programming Language :: Python :: 3
Classifier: Programming Language :: Python :: 3 :: Only
Classifier: Programming Language :: Python :: 3.10
Classifier: Programming Language :: Python :: 3.11
Classifier: Programming Language :: Python :: 3.12
Classifier: Programming Language :: Python :: 3.13
Classifier: Programming Language :: Python :: Implementation :: CPython
Classifier: Topic :: Software Development :: Libraries
Requires-Python: >=3.10
Requires-Dist: pydantic<3,>=2.5.2
Requires-Dist: pyserial<4,>=3.5
Provides-Extra: dev
Requires-Dist: build==1.2.2.post1; extra == 'dev'
Requires-Dist: twine==5.1.1; extra == 'dev'
Provides-Extra: test
Requires-Dist: freezegun==1.5.1; extra == 'test'
Requires-Dist: mypy==1.13.0; extra == 'test'
Requires-Dist: pytest-cov==6.0.0; extra == 'test'
Requires-Dist: pytest==8.3.3; extra == 'test'
Requires-Dist: ruff==0.7.1; extra == 'test'
